urlformat/__init__.py
urlformat/errors.py
urlformat/robotparser.py
urlformat/urlbuilder.py
urlformat/urlparser.py
urlformat-0.1.1.dist-info/LICENSE
urlformat-0.1.1.dist-info/METADATA
urlformat-0.1.1.dist-info/WHEEL
urlformat-0.1.1.dist-info/top_level.txt
urlformat-0.1.1.dist-info/RECORD
