Metadata-Version: 2.1
Name: urlformat
Version: 0.1.1
Summary: A package for formatting valid URL's.
Home-page: https://github.com/ChristopherBilg/urlformat
Author: Christopher Richard Bilger
Author-email: christopherbigl@gmail.com
License: GNU General Public License v2 (GPLv2)
Keywords: url format uri web address website search index
Platform: UNKNOWN
Classifier: Programming Language :: Python :: 3 :: Only
Classifier: License :: OSI Approved :: GNU General Public License v2 (GPLv2)
Classifier: Operating System :: OS Independent
Classifier: Development Status :: 2 - Pre-Alpha
Classifier: Environment :: Web Environment
Classifier: Topic :: Internet :: WWW/HTTP
Classifier: Topic :: Software Development :: Libraries
Classifier: Intended Audience :: Developers
Classifier: Natural Language :: English
Requires-Python: >=3.3
